sompy/__init__.py
sompy/codebook.py
sompy/decorators.py
sompy/neighborhood.py
sompy/normalization.py
sompy/sompy.py
sompy/visualization/__init__.py
sompy/visualization/bmuhits.py
sompy/visualization/dotmap.py
sompy/visualization/histogram.py
sompy/visualization/hitmap.py
sompy/visualization/mapview.py
sompy/visualization/plot_tools.py
sompy/visualization/plot_tools2.py
sompy/visualization/umatrix.py
sompy/visualization/view.py
som_py-1.1.1.dist-info/LICENSE
som_py-1.1.1.dist-info/METADATA
som_py-1.1.1.dist-info/WHEEL
som_py-1.1.1.dist-info/top_level.txt
som_py-1.1.1.dist-info/RECORD
